wc_onto/__init__.py
wc_onto/_version.py
wc_onto/core.py
wc_onto/onto.obo
wc_onto/config/__init__.py
wc_onto/config/core.default.cfg
wc_onto/config/core.py
wc_onto/config/core.schema.cfg
wc_onto-0.0.2.dist-info/LICENSE
wc_onto-0.0.2.dist-info/METADATA
wc_onto-0.0.2.dist-info/WHEEL
wc_onto-0.0.2.dist-info/entry_points.txt
wc_onto-0.0.2.dist-info/top_level.txt
wc_onto-0.0.2.dist-info/RECORD
